{
  "10%_none": 65.93,
  "10%_none_cutmix": 66.15,
  "10%_flip": 70.07,
  "10%_rotation_deg_15": 67.4,
  "10%_rotation_deg_30": 65.67,
  "10%_rotation_deg_90": 55.82,
  "10%_color_0.2": 65.63,
  "10%_color_0.3": 64.73,
  "10%_crop": 67.29,
  "25%_none": 71.49,
  "25%_none_cutmix": 73.87,
  "25%_flip": 75.01,
  "25%_rotation_deg_15": 74.52,
  "25%_rotation_deg_30": 73.3,
  "25%_rotation_deg_90": 63.87,
  "25%_color_0.2": 72.64,
  "25%_color_0.3": 72.73,
  "25%_crop": 74.86,
  "50%_none": 76.47,
  "50%_none_cutmix": 77.87,
  "50%_flip": 78.73,
  "50%_rotation_deg_15": 78.23,
  "50%_rotation_deg_30": 77.89,
  "50%_rotation_deg_90": 68.73,
  "50%_color_0.2": 76.06,
  "50%_color_0.3": 77.35,
  "50%_crop": 78.83,
  "100%_none": 80.54,
  "100%_none_cutmix": 80.83,
  "100%_flip": 82.77,
  "100%_rotation_deg_15": 81.84,
  "100%_rotation_deg_30": 80.63,
  "100%_rotation_deg_90": 72.46,
  "100%_color_0.2": 80.28,
  "100%_color_0.3": 80.45,
  "100%_crop": 82.5
}