{
  "10%_none": 66.12,
  "10%_crop_cutmix": 64.76,
  "10%_flip_rotation": 67.15,
  "10%_flip_crop": 67.7,
  "10%_flip_cutmix": 67.53,
  "10%_flip_color": 68.78,
  "10%_rotation_color": 67.61,
  "10%_rotation_crop": 64.51,
  "10%_rotation_deg_15_cutmix": 66.87,
  "10%_color_0.3_cutmix": 66.37,
  "10%_color_crop": 66.07,
  "25%_none": 72.19,
  "25%_crop_cutmix": 73.06,
  "25%_flip_rotation": 74.45,
  "25%_flip_crop": 75.82,
  "25%_flip_cutmix": 74.93,
  "25%_flip_color": 74.66,
  "25%_rotation_color": 73.7,
  "25%_rotation_crop": 73.84,
  "25%_rotation_deg_15_cutmix": 74.31,
  "25%_color_0.3_cutmix": 73.28,
  "25%_color_crop": 74.87,
  "50%_none": 75.88,
  "50%_crop_cutmix": 78.62,
  "50%_flip_rotation": 79.55,
  "50%_flip_crop": 79.57,
  "50%_flip_cutmix": 78.93,
  "50%_flip_color": 79.22,
  "50%_rotation_color": 78.55,
  "50%_rotation_crop": 78.32,
  "50%_rotation_deg_15_cutmix": 77.65,
  "50%_color_0.3_cutmix": 77.63,
  "50%_color_crop": 79.54,
  "100%_none": 80.64,
  "100%_crop_cutmix": 80.93,
  "100%_flip_rotation": 82.54,
  "100%_flip_crop": 81.65,
  "100%_flip_cutmix": 82.07,
  "100%_flip_color": 81.54,
  "100%_rotation_color": 81.8,
  "100%_rotation_crop": 81.18,
  "100%_rotation_deg_15_cutmix": 80.92,
  "100%_color_0.3_cutmix": 80.64,
  "100%_color_crop": 81.74
}